pyg_gui/__init__.py
pyg_gui/gui_elements/__init__.py
pyg_gui/gui_elements/button.py
pyg_gui/gui_elements/drop_down.py
pyg_gui/gui_elements/text_in.py
pyg_gui/gui_elements/text_out.py
pyg_gui/helper_files/__init__.py
pyg_gui/helper_files/text_class.py
pygame_gui_package-0.4.1.dist-info/LICENSE
pygame_gui_package-0.4.1.dist-info/METADATA
pygame_gui_package-0.4.1.dist-info/WHEEL
pygame_gui_package-0.4.1.dist-info/top_level.txt
pygame_gui_package-0.4.1.dist-info/RECORD
