Metadata-Version: 2.1
Name: pygame-gui-package
Version: 0.4.1
Summary: A gui package for pygame
Home-page: https://github.com/Almale02/pygame_gadsui_package
Author: SecondDanad
Author-email: not_trash@fake.hu
License: UNKNOWN
Project-URL: Github, https://github.com/Almale02/pygame_gui_package
Platform: UNKNOWN
Classifier: Programming Language :: Python :: 3
Classifier: License :: OSI Approved :: MIT License
Classifier: Operating System :: OS Independent
Requires-Python: >=3.10
License-File: LICENSE
